setup.py
apply_linkedin/__init__.py
apply_linkedin/models.py
apply_linkedin/parser.py
apply_linkedin/utils.py
apply_linkedin/django/__init__.py
apply_linkedin/django/decorators.py
apply_linkedin/django/models.py
apply_linkedin/django/signals.py
apply_linkedin/django/urls.py
apply_linkedin/django/views.py
python_apply_linkedin.egg-info/PKG-INFO
python_apply_linkedin.egg-info/SOURCES.txt
python_apply_linkedin.egg-info/dependency_links.txt
python_apply_linkedin.egg-info/top_level.txt