Metadata-Version: 1.0
Name: python-apply-linkedin
Version: 0.1.1
Summary: library that made easy implement Apply with Linkedin functionality
Home-page: https://github.com/rmaceissoft/python-apply-linkedin
Author: Reiner Marquez
Author-email: rmaceissoft@gmail.com
License: UNKNOWN
Platform: UNKNOWN
Classifier: Environment :: Web Environment
Classifier: Intended Audience :: Developers
Classifier: Operating System :: OS Independent
Classifier: Programming Language :: Python
Classifier: Topic :: Utilities
